dubao_g/__init__.py
dubao_g/_unit.py
dubao_g/nowcast.py
dubao_g-0.1.2.dist-info/METADATA
dubao_g-0.1.2.dist-info/WHEEL
dubao_g-0.1.2.dist-info/top_level.txt
dubao_g-0.1.2.dist-info/RECORD
