Metadata-Version: 2.1
Name: dubao-g
Version: 0.1.2
Summary: A brief description of your package
Home-page: https://github.com/yourusername/my_package
Author: Hungpc
Author-email: your.email@example.com
License: UNKNOWN
Platform: UNKNOWN
Classifier: Programming Language :: Python :: 3
Classifier: License :: OSI Approved :: MIT License
Classifier: Operating System :: OS Independent
Requires-Python: >=3.6
